skill_speed_test/LICENSE.md
skill_speed_test/README.md
skill_speed_test/__init__.py
skill_speed_test/skill.json
skill_speed_test/version.py
skill_speed_test/locale/en-us/dialog/notify_testing.dialog
skill_speed_test/locale/en-us/dialog/results.dialog
skill_speed_test/locale/en-us/dialog/start_test.dialog
skill_speed_test/locale/en-us/intent/run_speed_test.intent
skill_speed_test/neon_skill_speed_test.egg-info/PKG-INFO
skill_speed_test/neon_skill_speed_test.egg-info/SOURCES.txt
skill_speed_test/neon_skill_speed_test.egg-info/dependency_links.txt
skill_speed_test/neon_skill_speed_test.egg-info/entry_points.txt
skill_speed_test/neon_skill_speed_test.egg-info/requires.txt
skill_speed_test/neon_skill_speed_test.egg-info/top_level.txt
skill_speed_test/test/test_skill.py
neon_skill_speed_test-1.0.4.dist-info/LICENSE.md
neon_skill_speed_test-1.0.4.dist-info/METADATA
neon_skill_speed_test-1.0.4.dist-info/WHEEL
neon_skill_speed_test-1.0.4.dist-info/entry_points.txt
neon_skill_speed_test-1.0.4.dist-info/top_level.txt
neon_skill_speed_test-1.0.4.dist-info/RECORD
